[
  {
    "nim": "120140065",
    "nama": "M. Duta Faturrahman",
    "prodi": "Teknik Informatika"
  },
  {
    "nim": "120140118",
    "nama": "Rahman Pajri",
    "prodi": "Teknik Informatika"
  },
  {
    "nim": "120140109",
    "nama": "Alfian Kafilah Ba'its",
    "prodi": "Teknik Informatika"
  },
  {
    "nim": "120140098",
    "nama": "Bayu Nindioko",
    "prodi": "Teknik Informatika"
  },
  {
    "nim": "120170022",
    "nama": "Ujang Saputra",
    "prodi": "Teknik Sipil"
  },
  {
    "nim": "120170097",
    "nama": "Nanda Prasetyo",
    "prodi": "Teknik Sipil"
  },
  {
    "nim": "120170121",
    "nama": "Liza Maharani",
    "prodi": "Teknik Sipil"
  },
  {
    "nim": "120170111",
    "nama": "Din Samsudin",
    "prodi": "Teknik Sipil"
  },
  {
    "nim": "120160076",
    "nama": "Faisal Basri",
    "prodi": "Teknik Geofisika"
  },
  {
    "nim": "120160220",
    "nama": "Toni Sucipto",
    "prodi": "Teknik Geofisika"
  },
  {
    "nim": "120160056",
    "nama": "Shepia",
    "prodi": "Teknik Geofisika"
  },

  {
    "nim": "120160012",
    "nama": "Fima Abdullah",
    "prodi": "Teknik Geofisika"
  },
  {
    "nim": "120130086",
    "nama": "Shinta Agum Pertiwi",
    "prodi": "Perencanaan Wilayah dan Kota"
  },
  {
    "nim": "120130145",
    "nama": "Cindy Mariska",
    "prodi": "Perencanaan Wilayah dan Kota"
  },
  {
    "nim": "120130090",
    "nama": "Devi Yunida",
    "prodi": "Perencanaan Wilayah dan Kota"
  }
]
